dfcached/__init__.py
dfcached/_integrity.py
dfcached/_io.py
dfcached/_key.py
dfcached/_lock.py
dfcached/decorator.py
dfcached/py.typed
dfcached/utils.py
dfcached-0.3.0.dist-info/METADATA
dfcached-0.3.0.dist-info/WHEEL
dfcached-0.3.0.dist-info/licenses/LICENSE
dfcached-0.3.0.dist-info/RECORD
